datameta_client_lib/__init__.py
datameta_client_lib/api_client.py
datameta_client_lib/configuration.py
datameta_client_lib/exceptions.py
datameta_client_lib/model_utils.py
datameta_client_lib/rest.py
datameta_client_lib/api/__init__.py
datameta_client_lib/api/authentication_and_users_api.py
datameta_client_lib/api/files_api.py
datameta_client_lib/api/groups_api.py
datameta_client_lib/api/metadata_api.py
datameta_client_lib/api/remote_procedure_calls_api.py
datameta_client_lib/api/server_api.py
datameta_client_lib/api/services_api.py
datameta_client_lib/api/settings_api.py
datameta_client_lib/api/submissions_api.py
datameta_client_lib/api/user_api.py
datameta_client_lib/apis/__init__.py
datameta_client_lib/model/__init__.py
datameta_client_lib/model/api_key_list.py
datameta_client_lib/model/app_settings_response.py
datameta_client_lib/model/app_settings_update_request.py
datameta_client_lib/model/create_token_request.py
datameta_client_lib/model/error.py
datameta_client_lib/model/error_model.py
datameta_client_lib/model/file_announcement.py
datameta_client_lib/model/file_response.py
datameta_client_lib/model/file_update_request.py
datameta_client_lib/model/file_upload_response.py
datameta_client_lib/model/file_url.py
datameta_client_lib/model/group_response.py
datameta_client_lib/model/group_submissions.py
datameta_client_lib/model/group_update_request.py
datameta_client_lib/model/identifier.py
datameta_client_lib/model/meta_data_response.py
datameta_client_lib/model/meta_data_set.py
datameta_client_lib/model/meta_data_set_response.py
datameta_client_lib/model/meta_data_set_service_execution.py
datameta_client_lib/model/meta_datum.py
datameta_client_lib/model/meta_datum_response.py
datameta_client_lib/model/nullable_identifier.py
datameta_client_lib/model/password_change.py
datameta_client_lib/model/register_settings_response.py
datameta_client_lib/model/registration_request.py
datameta_client_lib/model/server_info_response.py
datameta_client_lib-1.4.0.dist-info/LICENSE
datameta_client_lib-1.4.0.dist-info/METADATA
datameta_client_lib-1.4.0.dist-info/WHEEL
datameta_client_lib-1.4.0.dist-info/top_level.txt
datameta_client_lib-1.4.0.dist-info/RECORD
