Metadata-Version: 2.1
Name: datameta-client-lib
Version: 1.4.0
Summary: DataMeta
Home-page: UNKNOWN
Author: DataMeta Dev Team
Author-email: leon.kuchenbecker@uni-tuebingen.de
License: UNKNOWN
Keywords: OpenAPI,OpenAPI-Generator,DataMeta
Platform: UNKNOWN
Requires-Python: >=3.6
License-File: LICENSE
Requires-Dist: urllib3 (>=1.25.3)
Requires-Dist: python-dateutil
